beatpy/__init__.py
beatpy/plot/__init__.py
beatpy/plot/_plot.py
beatpy-0.0.3.dist-info/licenses/LICENCE
drum_machine/__init__.py
drum_machine/const.py
drum_machine/phrases.py
drum_machine/player.py
drum_machine/samples.py
drum_machine/entities/__init__.py
drum_machine/entities/pattern.py
pgstudio/__init__.py
pgstudio/client.py
pgstudio/color.py
pgstudio/scene.py
pgstudio/_core/__init__.py
pgstudio/_core/clock.py
pgstudio/_core/window.py
tests/__init__.py
tests/conftest.py
tests/test_audio/__init__.py
tests/test_spotipy/__init__.py
tests/test_spotipy/test_get_related_artirsts.py
beatpy-0.0.3.dist-info/METADATA
beatpy-0.0.3.dist-info/WHEEL
beatpy-0.0.3.dist-info/top_level.txt
beatpy-0.0.3.dist-info/RECORD
