Metadata-Version: 2.4
Name: beatpy
Version: 0.0.3
Summary: Análisis de audio.
Home-page: https://pypi.org/project/beatpy/
Author: Alejo Prieto Dávalos
Project-URL: Source, https://github.com/AlejoPrietoDavalos/beatpy/
Requires-Python: >=3.11
License-File: LICENCE
Requires-Dist: yt_dlp>=2025.1.26
Requires-Dist: requests>=2.32.3
Requires-Dist: fastapi>=0.115.8
Requires-Dist: uvicorn>=0.34.0
Requires-Dist: numpy>=2.1.3
Requires-Dist: librosa>=0.11.0
Requires-Dist: soundfile>=0.13.1
Requires-Dist: matplotlib>=3.10.1
Requires-Dist: python-dotenv>=1.1.0
Dynamic: author
Dynamic: description
Dynamic: description-content-type
Dynamic: home-page
Dynamic: license-file
Dynamic: project-url
Dynamic: requires-dist
Dynamic: requires-python
Dynamic: summary
